datasette_transactions/__init__.py
datasette_transactions/client.py
datasette_transactions-0.1a0.dist-info/licenses/LICENSE
datasette_transactions-0.1a0.dist-info/METADATA
datasette_transactions-0.1a0.dist-info/WHEEL
datasette_transactions-0.1a0.dist-info/entry_points.txt
datasette_transactions-0.1a0.dist-info/top_level.txt
datasette_transactions-0.1a0.dist-info/RECORD
