Metadata-Version: 2.4
Name: datasette-transactions
Version: 0.1a0
Summary: API for executing multiple queries within a transaction
Author: Datasette
License-Expression: Apache-2.0
Project-URL: Homepage, https://github.com/datasette/datasette-transactions
Project-URL: Changelog, https://github.com/datasette/datasette-transactions/releases
Project-URL: Issues, https://github.com/datasette/datasette-transactions/issues
Project-URL: CI, https://github.com/datasette/datasette-transactions/actions
Classifier: Framework :: Datasette
Requires-Python: >=3.10
License-File: LICENSE
Requires-Dist: datasette>=1.0a22
Requires-Dist: httpx>=0.25
Dynamic: license-file
